beam_controller/__init__.py
beam_controller/__main__.py
beam_controller/beam_controller.py
beam_controller-0.1.1.dist-info/DESCRIPTION.rst
beam_controller-0.1.1.dist-info/METADATA
beam_controller-0.1.1.dist-info/RECORD
beam_controller-0.1.1.dist-info/WHEEL
beam_controller-0.1.1.dist-info/entry_points.txt
beam_controller-0.1.1.dist-info/metadata.json
beam_controller-0.1.1.dist-info/top_level.txt
