Metadata-Version: 2.0
Name: beam-controller
Version: 0.1.1
Summary: UNKNOWN
Home-page: https://git.kern.phys.au.dk/Munken/beam_controller
Author: Michael Munch
Author-email: mm@phys.au.dk
License: MIT
Platform: UNKNOWN
Requires-Dist: pyserial
